[
  {
    "IdName": "Paragon_Barb_00",
    "Name": "开始"
  },
  {
    "IdName": "Paragon_Barb_01",
    "Name": "出血"
  },
  {
    "IdName": "Paragon_Barb_02",
    "Name": "血怒"
  },
  {
    "IdName": "Paragon_Barb_03",
    "Name": "屠戮者"
  },
  {
    "IdName": "Paragon_Barb_04",
    "Name": "残杀者"
  },
  {
    "IdName": "Paragon_Barb_05",
    "Name": "碎骨者"
  },
  {
    "IdName": "Paragon_Barb_06",
    "Name": "无瑕技法"
  },
  {
    "IdName": "Paragon_Barb_07",
    "Name": "战争使者"
  },
  {
    "IdName": "Paragon_Barb_08",
    "Name": "武器大师"
  },
  {
    "IdName": "Paragon_Barb_10",
    "Name": "自然之力"
  },
  {
    "IdName": "Paragon_Druid_00",
    "Name": "开始"
  },
  {
    "IdName": "Paragon_Druid_01",
    "Name": "雷霆打击"
  },
  {
    "IdName": "Paragon_Druid_02",
    "Name": "大地灭绝"
  },
  {
    "IdName": "Paragon_Druid_03",
    "Name": "生存本能"
  },
  {
    "IdName": "Paragon_Druid_04",
    "Name": "杀戮欲望"
  },
  {
    "IdName": "Paragon_Druid_05",
    "Name": "恶念加重"
  },
  {
    "IdName": "Paragon_Druid_06",
    "Name": "内心的野兽"
  },
  {
    "IdName": "Paragon_Druid_07",
    "Name": "紧缩卷须"
  },
  {
    "IdName": "Paragon_Druid_08",
    "Name": "先祖指引"
  },
  {
    "IdName": "Paragon_Druid_10",
    "Name": "无羁"
  },
  {
    "IdName": "Paragon_Necro_00",
    "Name": "开始"
  },
  {
    "IdName": "Paragon_Necro_01",
    "Name": "邪信领袖"
  },
  {
    "IdName": "Paragon_Necro_02",
    "Name": "魁梧畸体"
  },
  {
    "IdName": "Paragon_Necro_03",
    "Name": "肉食者"
  },
  {
    "IdName": "Paragon_Necro_04",
    "Name": "死亡气息"
  },
  {
    "IdName": "Paragon_Necro_05",
    "Name": "骨骼移植"
  },
  {
    "IdName": "Paragon_Necro_06",
    "Name": "气血双生"
  },
  {
    "IdName": "Paragon_Necro_07",
    "Name": "血浴"
  },
  {
    "IdName": "Paragon_Necro_08",
    "Name": "枯萎凋零"
  },
  {
    "IdName": "Paragon_Necro_10",
    "Name": "脆弱"
  },
  {
    "IdName": "Paragon_Paladin_00",
    "Name": "开始"
  },
  {
    "IdName": "Paragon_Paladin_01",
    "Name": "壁垒"
  },
  {
    "IdName": "Paragon_Paladin_02",
    "Name": "负盾者"
  },
  {
    "IdName": "Paragon_Paladin_03",
    "Name": "激昂"
  },
  {
    "IdName": "Paragon_Paladin_04",
    "Name": "布道者"
  },
  {
    "IdName": "Paragon_Paladin_05",
    "Name": "神性"
  },
  {
    "IdName": "Paragon_Paladin_06",
    "Name": "不懈"
  },
  {
    "IdName": "Paragon_Paladin_07",
    "Name": "裁决"
  },
  {
    "IdName": "Paragon_Paladin_08",
    "Name": "坚忍"
  },
  {
    "IdName": "Paragon_Paladin_09",
    "Name": "信标"
  },
  {
    "IdName": "Paragon_Rogue_00",
    "Name": "开始"
  },
  {
    "IdName": "Paragon_Rogue_01",
    "Name": "怪异赏金"
  },
  {
    "IdName": "Paragon_Rogue_02",
    "Name": "交易骗术"
  },
  {
    "IdName": "Paragon_Rogue_03",
    "Name": "卑鄙招数"
  },
  {
    "IdName": "Paragon_Rogue_04",
    "Name": "致命伏击"
  },
  {
    "IdName": "Paragon_Rogue_05",
    "Name": "莱拉娜的本能"
  },
  {
    "IdName": "Paragon_Rogue_06",
    "Name": "不留证人"
  },
  {
    "IdName": "Paragon_Rogue_07",
    "Name": "直击弱点"
  },
  {
    "IdName": "Paragon_Rogue_08",
    "Name": "狡诈计谋"
  },
  {
    "IdName": "Paragon_Rogue_10",
    "Name": "死亡之舞"
  },
  {
    "IdName": "Paragon_Sorc_00",
    "Name": "开始"
  },
  {
    "IdName": "Paragon_Sorc_01",
    "Name": "灼烧之热"
  },
  {
    "IdName": "Paragon_Sorc_02",
    "Name": "冰冷命运"
  },
  {
    "IdName": "Paragon_Sorc_03",
    "Name": "静电奔涌"
  },
  {
    "IdName": "Paragon_Sorc_04",
    "Name": "元素召唤师"
  },
  {
    "IdName": "Paragon_Sorc_05",
    "Name": "燃烧本能"
  },
  {
    "IdName": "Paragon_Sorc_06",
    "Name": "陨冰"
  },
  {
    "IdName": "Paragon_Sorc_07",
    "Name": "不灭导体"
  },
  {
    "IdName": "Paragon_Sorc_08",
    "Name": "附魔大师"
  },
  {
    "IdName": "Paragon_Sorc_10",
    "Name": "元能释放"
  },
  {
    "IdName": "Paragon_Spirit_0",
    "Name": "开始"
  },
  {
    "IdName": "Paragon_Spirit_01",
    "Name": "见招拆招"
  },
  {
    "IdName": "Paragon_Spirit_02",
    "Name": "多刺棘皮"
  },
  {
    "IdName": "Paragon_Spirit_03",
    "Name": "粘性护盾"
  },
  {
    "IdName": "Paragon_Spirit_04",
    "Name": "辛烈猛药"
  },
  {
    "IdName": "Paragon_Spirit_05",
    "Name": "攻瑕蹈隙"
  },
  {
    "IdName": "Paragon_Spirit_06",
    "Name": "驱动"
  },
  {
    "IdName": "Paragon_Spirit_07",
    "Name": "灵能汇流"
  },
  {
    "IdName": "Paragon_Spirit_08",
    "Name": "削弱"
  }
]