[
  {
    "IdSno": 1314229,
    "IdName": "DungeonAffix_Positive_DamageReductionForMissingHealth",
    "Name": "久戰不懈",
    "Description": "你每失去 10% 生命值，傷害減免就會提高 6%。",
    "DungeonZoneInfo": "",
    "Type": "Positive"
  },
  {
    "IdSno": 410196226,
    "IdName": "ItemDungeonAffixResses",
    "Name": "允許重生：",
    "Description": "",
    "DungeonZoneInfo": "",
    "Type": "Misc"
  },
  {
    "IdSno": 1582559,
    "IdName": "DungeonAffix_Major_Elemental_Totems",
    "Name": "元素圖騰",
    "Description": "元素圖騰會在戰鬥中隨機出現，若出現 5 秒後未被摧毀，將強化附近敵人。",
    "DungeonZoneInfo": "",
    "Type": "Major"
  },
  {
    "IdSno": 1828297,
    "IdName": "DungeonAffix_Positive_GlyphXP",
    "Name": "先人恩惠",
    "Description": "完成此地城時獲得的雕紋經驗值提高 20%。",
    "DungeonZoneInfo": "",
    "Type": "Positive"
  },
  {
    "IdSno": 1894518,
    "IdName": "DungeonAffix_Positive_GlyphXP_EvergreenVersion",
    "Name": "先祖恩惠",
    "Description": "完成此地城時獲得的雕紋經驗值提高 20%。",
    "DungeonZoneInfo": "",
    "Type": "Positive"
  },
  {
    "IdSno": 1894221,
    "IdName": "DungeonAffix_Major_Boss_MegaDemon_Tier96",
    "Name": "冰中巨獸",
    "Description": "在冰凍洞穴的盡頭勇敢面對更具挑戰性的冰中巨獸。",
    "DungeonZoneInfo": "",
    "Type": "Major"
  },
  {
    "IdSno": 1314248,
    "IdName": "DungeonAffix_Positive_FrostDamage",
    "Name": "冰霜傷害",
    "Description": "你造成的冰霜傷害提高 15%。",
    "DungeonZoneInfo": "",
    "Type": "Positive"
  },
  {
    "IdSno": 1314288,
    "IdName": "DungeonAffix_Positive_StunCausesBurning",
    "Name": "受控場時爆炸",
    "Description": "遭到控場效果擊中時，會在你周圍產生爆炸。",
    "DungeonZoneInfo": "",
    "Type": "Positive"
  },
  {
    "IdSno": 1314252,
    "IdName": "DungeonAffix_Major_Nightmare Portal",
    "Name": "夢魘傳送門",
    "Description": "戰鬥時夢魘傳送門會在玩家附近隨機開啟，湧出危險的怪物。",
    "DungeonZoneInfo": "",
    "Type": "Major"
  },
  {
    "IdSno": 1314450,
    "IdName": "DungeonAffix_Minor_Monster_BarrierKiller",
    "Name": "屏障破壞者",
    "Description": "怪物對屏障造成的傷害提高 100%。",
    "DungeonZoneInfo": "",
    "Type": "Minor"
  },
  {
    "IdSno": 1314344,
    "IdName": "DungeonAffix_Major_Empowered Elites (Frost)",
    "Name": "強化精英怪物（冰寒附魔）",
    "Description": "精英怪物必定有「冰寒附魔」屬性。",
    "DungeonZoneInfo": "",
    "Type": "Major"
  },
  {
    "IdSno": 1314333,
    "IdName": "DungeonAffix_Major_Empowered Elites (Suppressor)",
    "Name": "強化精英怪物（抑制者）",
    "Description": "精英怪物必定有「抑制者」屬性。",
    "DungeonZoneInfo": "",
    "Type": "Major"
  },
  {
    "IdSno": 1314346,
    "IdName": "DungeonAffix_Major_Empowered Elites (Shadow)",
    "Name": "強化精英怪物（暗影附魔）",
    "Description": "精英怪物必定有「暗影附魔」屬性。",
    "DungeonZoneInfo": "",
    "Type": "Major"
  },
  {
    "IdSno": 1314342,
    "IdName": "DungeonAffix_Major_Empowered Elites (Poison)",
    "Name": "強化精英怪物（毒素附魔）",
    "Description": "精英怪物必定有「毒素附魔」屬性。",
    "DungeonZoneInfo": "",
    "Type": "Major"
  },
  {
    "IdSno": 1314335,
    "IdName": "DungeonAffix_Major_Empowered Elites (Teleporter)",
    "Name": "強化精英怪物（瞬移）",
    "Description": "精英怪物必定有「瞬移」屬性。",
    "DungeonZoneInfo": "",
    "Type": "Major"
  },
  {
    "IdSno": 1314339,
    "IdName": "DungeonAffix_Major_Empowered Elites (Electric Lance)",
    "Name": "強化精英怪物（電光）",
    "Description": "精英怪物必定有「電能長槍」屬性。",
    "DungeonZoneInfo": "",
    "Type": "Major"
  },
  {
    "IdSno": 1314260,
    "IdName": "DungeonAffix_Major_Avenger",
    "Name": "復仇者",
    "Description": "殺死怪物會在短暫延遲後激怒周圍的怪物，使其造成的傷害提高。",
    "DungeonZoneInfo": "",
    "Type": "Major"
  },
  {
    "IdSno": 1314415,
    "IdName": "DungeonAffix_Minor_Monster_ExtraCold",
    "Name": "怪物冰寒傷害",
    "Description": "怪物額外造成等同其 20% 物理傷害的冰寒傷害。",
    "DungeonZoneInfo": "",
    "Type": "Minor"
  },
  {
    "IdSno": 1314397,
    "IdName": "DungeonAffix_Minor_Monster_LessCold",
    "Name": "怪物冰寒抵抗",
    "Description": "怪物受到的冰寒傷害降低 40%。",
    "DungeonZoneInfo": "",
    "Type": "Minor"
  },
  {
    "IdSno": 1314444,
    "IdName": "DungeonAffix_Minor_Monster_AntiOverpower",
    "Name": "怪物壓制抵抗",
    "Description": "怪物的攻擊會使你的下一個壓制傷害降低 12%，最多可堆疊至 60%。",
    "DungeonZoneInfo": "",
    "Type": "Minor"
  },
  {
    "IdSno": 1898340,
    "IdName": "DungeonAffix_Major_Monster_Barrier",
    "Name": "怪物屏障",
    "Description": "Monsters gain 85% of their Maximum Life as a Barrier.",
    "DungeonZoneInfo": "",
    "Type": "Major"
  },
  {
    "IdSno": 1314446,
    "IdName": "DungeonAffix_Minor_Monster_AntiCC",
    "Name": "怪物控場抵抗",
    "Description": "怪物受到控場的持續時間縮短 40%。",
    "DungeonZoneInfo": "",
    "Type": "Minor"
  },
  {
    "IdSno": 1314354,
    "IdName": "DungeonAffix_Minor_Monster_AttackFaster",
    "Name": "怪物攻擊速度",
    "Description": "怪物攻擊速度提高 25%。",
    "DungeonZoneInfo": "",
    "Type": "Minor"
  },
  {
    "IdSno": 1314442,
    "IdName": "DungeonAffix_Minor_Monster_AntiVulnerable",
    "Name": "怪物易傷抵抗",
    "Description": "怪物受到易傷效果的持續時間縮短 60%。",
    "DungeonZoneInfo": "",
    "Type": "Minor"
  },
  {
    "IdSno": 1314411,
    "IdName": "DungeonAffix_Minor_Monster_ExtraShadow",
    "Name": "怪物暗影傷害",
    "Description": "怪物額外造成等同其 20% 物理傷害的暗影傷害。",
    "DungeonZoneInfo": "",
    "Type": "Minor"
  },
  {
    "IdSno": 1314376,
    "IdName": "DungeonAffix_Minor_Monster_LessShadow",
    "Name": "怪物暗影抵抗",
    "Description": "怪物受到的暗影傷害降低 40%。",
    "DungeonZoneInfo": "",
    "Type": "Minor"
  },
  {
    "IdSno": 1314399,
    "IdName": "DungeonAffix_Minor_Monster_ExtraCorruption",
    "Name": "怪物暗影持續傷害",
    "Description": "怪物在 5 秒內額外造成等同其 30% 物理傷害的暗影傷害。",
    "DungeonZoneInfo": "",
    "Type": "Minor"
  },
  {
    "IdSno": 1314378,
    "IdName": "DungeonAffix_Minor_Monster_LessCorruption",
    "Name": "怪物暗影持續傷害抗性",
    "Description": "怪物受到你的暗影持續傷害效果降低 60%。",
    "DungeonZoneInfo": "",
    "Type": "Minor"
  },
  {
    "IdSno": 1314405,
    "IdName": "DungeonAffix_Minor_Monster_ExtraPoison",
    "Name": "怪物毒素傷害",
    "Description": "怪物在 5 秒內額外造成等同其 30% 物理傷害的毒素傷害。",
    "DungeonZoneInfo": "",
    "Type": "Minor"
  },
  {
    "IdSno": 1314393,
    "IdName": "DungeonAffix_Minor_Monster_LessPoison",
    "Name": "怪物毒素抵抗",
    "Description": "怪物受到的毒素傷害降低 60%。",
    "DungeonZoneInfo": "",
    "Type": "Minor"
  },
  {
    "IdSno": 1314407,
    "IdName": "DungeonAffix_Minor_Monster_ExtraBleeding",
    "Name": "怪物流血傷害",
    "Description": "怪物在 5 秒內額外造成等同其 30% 物理傷害的流血傷害。",
    "DungeonZoneInfo": "",
    "Type": "Minor"
  },
  {
    "IdSno": 1314380,
    "IdName": "DungeonAffix_Minor_Monster_LessBleeding",
    "Name": "怪物流血抵抗",
    "Description": "怪物受到的流血傷害降低 60%。",
    "DungeonZoneInfo": "",
    "Type": "Minor"
  },
  {
    "IdSno": 1314424,
    "IdName": "DungeonAffix_Minor_Monster_ExtraFire",
    "Name": "怪物火焰傷害",
    "Description": "怪物額外造成等同其 20% 物理傷害的火焰傷害。",
    "DungeonZoneInfo": "",
    "Type": "Minor"
  },
  {
    "IdSno": 1314437,
    "IdName": "DungeonAffix_Minor_Monster_LessFire",
    "Name": "怪物火焰抵抗",
    "Description": "怪物受到的火焰傷害降低 40%。",
    "DungeonZoneInfo": "",
    "Type": "Minor"
  },
  {
    "IdSno": 1314409,
    "IdName": "DungeonAffix_Minor_Monster_ExtraBurning",
    "Name": "怪物燃燒傷害",
    "Description": "怪物在 5 秒內額外造成等同其 30% 物理傷害的燃燒傷害。",
    "DungeonZoneInfo": "",
    "Type": "Minor"
  },
  {
    "IdSno": 1314382,
    "IdName": "DungeonAffix_Minor_Monster_LessBurning",
    "Name": "怪物燃燒抵抗",
    "Description": "怪物受到的燃燒傷害降低 60%。",
    "DungeonZoneInfo": "",
    "Type": "Minor"
  },
  {
    "IdSno": 1314448,
    "IdName": "DungeonAffix_Minor_Monster_AntiCrit",
    "Name": "怪物爆擊抵抗",
    "Description": "怪物的攻擊使你的爆擊傷害降低 6%，持續 3 秒。最多可堆疊至 60 %。",
    "DungeonZoneInfo": "",
    "Type": "Minor"
  },
  {
    "IdSno": 1314388,
    "IdName": "DungeonAffix_Minor_Monster_LessPhysical",
    "Name": "怪物物理抵抗",
    "Description": "怪物受到的物理傷害降低 30%。",
    "DungeonZoneInfo": "",
    "Type": "Minor"
  },
  {
    "IdSno": 1314356,
    "IdName": "DungeonAffix_Minor_Monster_HPBonus",
    "Name": "怪物生命值",
    "Description": "怪物獲得 30% 額外生命值。",
    "DungeonZoneInfo": "",
    "Type": "Minor"
  },
  {
    "IdSno": 1314454,
    "IdName": "DungeonAffix_Minor_Monster_HPRegen",
    "Name": "怪物生命值恢復",
    "Description": "非首領怪物每秒恢復生命值上限的 1.5%。",
    "DungeonZoneInfo": "",
    "Type": "Minor"
  },
  {
    "IdSno": 1314372,
    "IdName": "DungeonAffix_Minor_Monster_LifeSteal",
    "Name": "怪物生命竊取",
    "Description": "非首領怪物獲得 15% 生命竊取。",
    "DungeonZoneInfo": "",
    "Type": "Minor"
  },
  {
    "IdSno": 966310656,
    "IdName": "MonsterLevel",
    "Name": "怪物等級：",
    "Description": "",
    "DungeonZoneInfo": "",
    "Type": "Misc"
  },
  {
    "IdSno": 1314360,
    "IdName": "DungeonAffix_Minor_Monster_ReflectNonPhysical",
    "Name": "怪物荊棘",
    "Description": "怪物反彈 8% 傷害。",
    "DungeonZoneInfo": "",
    "Type": "Minor"
  },
  {
    "IdSno": 1314413,
    "IdName": "DungeonAffix_Minor_Monster_ExtraLightning",
    "Name": "怪物電擊傷害",
    "Description": "怪物額外造成等同其 20% 物理傷害的電擊傷害。",
    "DungeonZoneInfo": "",
    "Type": "Minor"
  },
  {
    "IdSno": 1314395,
    "IdName": "DungeonAffix_Minor_Monster_LessLightning",
    "Name": "怪物電擊抵抗",
    "Description": "怪物受到的電擊傷害降低 40%。",
    "DungeonZoneInfo": "",
    "Type": "Minor"
  },
  {
    "IdSno": 1314417,
    "IdName": "DungeonAffix_Minor_Monster_ReduceResistance",
    "Name": "抗性破壞者",
    "Description": "從遠處攻擊的怪物會使全元素抗性降低 5%，持續 6 秒，最多可堆疊至 25%。",
    "DungeonZoneInfo": "",
    "Type": "Minor"
  },
  {
    "IdSno": 1314391,
    "IdName": "DungeonAffix_Positive_EvadePushesEnemies",
    "Name": "推撞閃避",
    "Description": "使用閃避可擊退敵人。",
    "DungeonZoneInfo": "",
    "Type": "Positive"
  },
  {
    "IdSno": 1314233,
    "IdName": "DungeonAffix_Positive_CooldownReductionOnKill",
    "Name": "擊殺時冷卻時間縮短",
    "Description": "擊殺一隻怪物可使你的冷卻時間縮短 0.25 秒。",
    "DungeonZoneInfo": "",
    "Type": "Positive"
  },
  {
    "IdSno": 1314231,
    "IdName": "DungeonAffix_Positive_ShadowDamage",
    "Name": "暗影傷害",
    "Description": "你造成的暗影傷害提高 15%。",
    "DungeonZoneInfo": "",
    "Type": "Positive"
  },
  {
    "IdSno": 1314350,
    "IdName": "DungeonAffix_Major_DeathPulse",
    "Name": "死亡衝擊",
    "Description": "擊殺怪物時，會在短暫延遲後釋放致命的暗影脈衝。",
    "DungeonZoneInfo": "",
    "Type": "Major"
  },
  {
    "IdSno": 1314227,
    "IdName": "DungeonAffix_Positive_PoisonDamage",
    "Name": "毒素傷害",
    "Description": "你造成的毒素傷害提高 15%。",
    "DungeonZoneInfo": "",
    "Type": "Positive"
  },
  {
    "IdSno": 1314358,
    "IdName": "DungeonAffix_Positive_EvadeLeavesPoison",
    "Name": "毒素閃避",
    "Description": "使用閃避會在你穿過的第一個敵人或是你的最終位置留下一灘毒素傷害池。",
    "DungeonZoneInfo": "",
    "Type": "Positive"
  },
  {
    "IdSno": 1314246,
    "IdName": "DungeonAffix_Positive_IncreasedHealing",
    "Name": "治療效果提高",
    "Description": "你的治療接受效果提高 15%。",
    "DungeonZoneInfo": "",
    "Type": "Positive"
  },
  {
    "IdSno": 1314256,
    "IdName": "DungeonAffix_Major_Volcanic",
    "Name": "火山",
    "Description": "戰鬥時，會定期在玩家附近引發火焰。",
    "DungeonZoneInfo": "",
    "Type": "Major"
  },
  {
    "IdSno": 1314313,
    "IdName": "DungeonAffix_Positive_FireDamage",
    "Name": "火焰傷害",
    "Description": "你造成的火焰傷害提高 15%。",
    "DungeonZoneInfo": "",
    "Type": "Positive"
  },
  {
    "IdSno": 1690800,
    "IdName": "DungeonAffix_Minor_Monster_Traps_Fire01",
    "Name": "火焰陷阱",
    "Description": "",
    "DungeonZoneInfo": "",
    "Type": "Minor"
  },
  {
    "IdSno": 1314366,
    "IdName": "DungeonAffix_Minor_Monster_Unstoppable",
    "Name": "無阻怪物",
    "Description": "怪物生命值低於 30% 時會進入無阻狀態。",
    "DungeonZoneInfo": "",
    "Type": "Minor"
  },
  {
    "IdSno": 1314244,
    "IdName": "DungeonAffix_Positive_IncreasedCritChance",
    "Name": "爆擊提高",
    "Description": "你的爆擊機率提高 9%。",
    "DungeonZoneInfo": "",
    "Type": "Positive"
  },
  {
    "IdSno": 1314293,
    "IdName": "DungeonAffix_Positive_PhysicalDamage",
    "Name": "物理傷害",
    "Description": "你造成的物理傷害提高 15%。",
    "DungeonZoneInfo": "",
    "Type": "Positive"
  },
  {
    "IdSno": 1314374,
    "IdName": "DungeonAffix_Minor_Monster_ChanceSlow",
    "Name": "緩速投射攻擊",
    "Description": "從遠處攻擊的怪物有 50% 機率緩速目標。",
    "DungeonZoneInfo": "",
    "Type": "Minor"
  },
  {
    "IdSno": 1314368,
    "IdName": "DungeonAffix_Minor_Monster_AttackBehind",
    "Name": "背刺者",
    "Description": "近距怪物於後方造成的攻擊會使你變得易傷。易傷狀態時受到的傷害提高 35%。",
    "DungeonZoneInfo": "",
    "Type": "Minor"
  },
  {
    "IdSno": 1314236,
    "IdName": "DungeonAffix_Positive_Thorns",
    "Name": "荊棘",
    "Description": "你在攻擊一名敵人後，荊棘傷害提高 200 點，持續 3 秒。最多可堆疊額外 1000 點。",
    "DungeonZoneInfo": "",
    "Type": "Positive"
  },
  {
    "IdSno": 1314370,
    "IdName": "DungeonAffix_Minor_Monster_ReduceHealing",
    "Name": "藥水破壞者",
    "Description": "從遠處攻擊的怪物會使你下個治療藥水冷卻時間延長 0.75 秒，最多 7 秒。",
    "DungeonZoneInfo": "",
    "Type": "Minor"
  },
  {
    "IdSno": 1314352,
    "IdName": "DungeonAffix_Major_Blood Blister",
    "Name": "血囊",
    "Description": "擊殺怪物有機率會產生血囊。在短時間後爆炸並造成大量範圍傷害。",
    "DungeonZoneInfo": "",
    "Type": "Major"
  },
  {
    "IdSno": 1314422,
    "IdName": "DungeonAffix_Minor_Monster_SunderArmor",
    "Name": "護甲破壞者",
    "Description": "從遠處攻擊的怪物會使你的護甲值降低 7%，持續 6 秒，最多可堆疊至 35%。",
    "DungeonZoneInfo": "",
    "Type": "Minor"
  },
  {
    "IdSno": 1314364,
    "IdName": "DungeonAffix_Minor_Monster_DrainResource",
    "Name": "資源燃燒",
    "Description": "在你消耗資源後，每當你被遠距敵人擊中還會額外燃燒所消耗資源的 30%。",
    "DungeonZoneInfo": "",
    "Type": "Minor"
  },
  {
    "IdSno": 1314297,
    "IdName": "DungeonAffix_Positive_AttackMoveSpeedOnKill",
    "Name": "迅捷殺手",
    "Description": "擊殺一隻怪物會使攻擊力與移動速度提高 2.0%。最多可堆疊至 20%。",
    "DungeonZoneInfo": "",
    "Type": "Positive"
  },
  {
    "IdSno": 1314384,
    "IdName": "DungeonAffix_Minor_Monster_LessMelee",
    "Name": "近戰防禦者",
    "Description": "怪物受到的近程目標傷害降低 40%。",
    "DungeonZoneInfo": "",
    "Type": "Minor"
  },
  {
    "IdSno": 1314211,
    "IdName": "DungeonAffix_Major_Drifting Shade",
    "Name": "遊蕩暗影",
    "Description": "遊蕩暗影會追逐玩家。接觸到玩家時爆炸，造成大量傷害，並製造夢魘場域使目標暈眩。",
    "DungeonZoneInfo": "",
    "Type": "Major"
  },
  {
    "IdSno": 1314386,
    "IdName": "DungeonAffix_Minor_Monster_LessRanged",
    "Name": "遠距防禦者",
    "Description": "怪物受到的遠程目標傷害降低 60%。",
    "DungeonZoneInfo": "",
    "Type": "Minor"
  },
  {
    "IdSno": 1314215,
    "IdName": "DungeonAffix_Positive_GoldFind",
    "Name": "金幣尋獲量",
    "Description": "你尋獲的金幣增加 30%。",
    "DungeonZoneInfo": "",
    "Type": "Positive"
  },
  {
    "IdSno": 1314420,
    "IdName": "DungeonAffix_Minor_Monster_ReduceDodge",
    "Name": "閃躲破壞者",
    "Description": "從遠處攻擊的怪物會使閃躲機率降低 12%，持續 6 秒，最多可堆疊至 60%。",
    "DungeonZoneInfo": "",
    "Type": "Minor"
  },
  {
    "IdSno": 1314217,
    "IdName": "DungeonAffix_Positive_PeriodicLightning",
    "Name": "閃電呼喚者",
    "Description": "你偶爾會召喚從天而降的閃電並對附近敵人造成傷害。",
    "DungeonZoneInfo": "",
    "Type": "Positive"
  },
  {
    "IdSno": 1314209,
    "IdName": "DungeonAffix_Major_Lightning Storm",
    "Name": "閃電風暴",
    "Description": "閃電集中於玩家上方。進入保護罩內以避免嚴重傷害。",
    "DungeonZoneInfo": "",
    "Type": "Major"
  },
  {
    "IdSno": 1314238,
    "IdName": "DungeonAffix_Positive_LightningDamage",
    "Name": "電擊傷害",
    "Description": "你造成的電擊傷害提高 15%。",
    "DungeonZoneInfo": "",
    "Type": "Positive"
  },
  {
    "IdSno": 1719009,
    "IdName": "DungeonAffix_Positive_ExtraShrines",
    "Name": "額外聖壇",
    "Description": "地城中會出現額外聖壇。",
    "DungeonZoneInfo": "",
    "Type": "Positive"
  },
  {
    "IdSno": 1314213,
    "IdName": "DungeonAffix_Major_StormbanesWrath",
    "Name": "風禍之怒",
    "Description": "風禍之怒會跟隨玩家，接觸到玩家時釋放致命衝擊。",
    "DungeonZoneInfo": "",
    "Type": "Major"
  },
  {
    "IdSno": 1314240,
    "IdName": "DungeonAffix_Positive_MagicFind",
    "Name": "魔寶尋獲率",
    "Description": "你會從敵人身上尋獲更多物品。",
    "DungeonZoneInfo": "",
    "Type": "Positive"
  }
]