[
  {
    "IdSno": 1113455,
    "IdName": "World_DGN_Hawe_AkkhansGrasp",
    "Name": "Akkhan's Grasp",
    "Description": "Evil and blood seep through the tomb's ruptured seals.",
    "Type": "Dungeon"
  },
  {
    "IdSno": 1113084,
    "IdName": "World_DGN_Hawe_AncientReservoir",
    "Name": "Ancient Reservoir",
    "Description": "A tainted wellspring runs under these ruins.",
    "Type": "Dungeon"
  },
  {
    "IdSno": 1314422,
    "IdName": "DungeonAffix_Minor_Monster_SunderArmor",
    "Name": "Armor Breakers",
    "Description": "Monster attacks from a distance reduce your Armor by 7% for 6 seconds, stacking up to 35%.",
    "Type": "Minor"
  },
  {
    "IdSno": 1314260,
    "IdName": "DungeonAffix_Major_Avenger",
    "Name": "Avenger",
    "Description": "Killing a monster enrages monsters near it after a short delay, making them dealing more damage.",
    "Type": "Major"
  },
  {
    "IdSno": 1314368,
    "IdName": "DungeonAffix_Minor_Monster_AttackBehind",
    "Name": "Backstabbers",
    "Description": "Monsters near the player deal 150% more damage when attacking from behind.",
    "Type": "Minor"
  },
  {
    "IdSno": 1314450,
    "IdName": "DungeonAffix_Minor_Monster_BarrierKiller",
    "Name": "Barrier Breakers",
    "Description": "Monsters deal 100% more damage to Barriers.",
    "Type": "Minor"
  },
  {
    "IdSno": 1114114,
    "IdName": "World_DGN_Hawe_BastionOfFaith",
    "Name": "Bastion of Faith",
    "Description": "Lost and starving, the knights became beasts.",
    "Type": "Dungeon"
  },
  {
    "IdSno": 1314229,
    "IdName": "DungeonAffix_Positive_DamageReductionForMissingHealth",
    "Name": "Battle Hardened",
    "Description": "Gain 6% damage reduction for every 10% Health you are missing.",
    "Type": "Positive"
  },
  {
    "IdSno": 1113981,
    "IdName": "World_DGN_Step_BetrayersRow",
    "Name": "Betrayer's Row",
    "Description": "The twisted remains of a town driven mad by envy. ",
    "Type": "Dungeon"
  },
  {
    "IdSno": 1314352,
    "IdName": "DungeonAffix_Major_Blood Blister",
    "Name": "Blood Blister",
    "Description": "Killing a monster has a chance to spawn a Blood Blister. After a short time, it explodes, dealing heavy area damage.",
    "Type": "Major"
  },
  {
    "IdSno": 1113766,
    "IdName": "World_DGN_Step_CharnelHouse",
    "Name": "Charnel House",
    "Description": "Bodies are stored here, some still alive. Food for demons.",
    "Type": "Dungeon"
  },
  {
    "IdSno": 1113350,
    "IdName": "World_DGN_Kehj_CollapsedVault",
    "Name": "Collapsed Vault",
    "Description": "In dead hands do these ancient treasures lie.",
    "Type": "Dungeon"
  },
  {
    "IdSno": 1314288,
    "IdName": "DungeonAffix_Positive_StunCausesBurning",
    "Name": "Control Impaired Explosions",
    "Description": "Being hit by Control Impairing Effects creates an explosion around you.",
    "Type": "Positive"
  },
  {
    "IdSno": 1113542,
    "IdName": "World_DGN_Frac_DeadMansDredge",
    "Name": "Dead Man's Dredge",
    "Description": "The predators that dwell in this cave hunt human game.",
    "Type": "Dungeon"
  },
  {
    "IdSno": 1314350,
    "IdName": "DungeonAffix_Major_DeathPulse",
    "Name": "Death Pulse",
    "Description": "Killing a monster releases a deadly lightning pulse after a short delay.",
    "Type": "Major"
  },
  {
    "IdSno": 1314420,
    "IdName": "DungeonAffix_Minor_Monster_ReduceDodge",
    "Name": "Dodge Breakers",
    "Description": "Monster attacks from a distance reduce dodge chance by 12% for 6 seconds,\u00A0stacking up to 60%.",
    "Type": "Minor"
  },
  {
    "IdSno": 1113857,
    "IdName": "World_DGN_Scos_DomhainneTunnels",
    "Name": "Domhainne Tunnels",
    "Description": "Corbach residents hear the screams from the Khazra’s lair.",
    "Type": "Dungeon"
  },
  {
    "IdSno": 1314211,
    "IdName": "DungeonAffix_Major_Drifting Shade",
    "Name": "Drifting Shade",
    "Description": "Drifting Shade chases players. Upon reaching them, it explodes for heavy damage and creates a Nightmare Field that Dazes victims.",
    "Type": "Major"
  },
  {
    "IdSno": 1314344,
    "IdName": "DungeonAffix_Major_Empowered Elites (Frost)",
    "Name": "Empowered Elites (Cold Enchanted)",
    "Description": "Elites always have the \"Cold Enchanted\" affix.",
    "Type": "Major"
  },
  {
    "IdSno": 1314342,
    "IdName": "DungeonAffix_Major_Empowered Elites (Poison)",
    "Name": "Empowered Elites (Poison Enchanted)",
    "Description": "Elites always have the \"Poison Enchanted\" affix.",
    "Type": "Major"
  },
  {
    "IdSno": 1314346,
    "IdName": "DungeonAffix_Major_Empowered Elites (Shadow)",
    "Name": "Empowered Elites (Shadow Enchanted)",
    "Description": "Elites always have the \"Shadow Enchanted\" affix.",
    "Type": "Major"
  },
  {
    "IdSno": 1314339,
    "IdName": "DungeonAffix_Major_Empowered Elites (Electric Lance)",
    "Name": "Empowered Elites (Shock Lance)",
    "Description": "Elites always have the \"Electric Lance\" affix.",
    "Type": "Major"
  },
  {
    "IdSno": 1314333,
    "IdName": "DungeonAffix_Major_Empowered Elites (Suppressor)",
    "Name": "Empowered Elites (Suppressor)",
    "Description": "Elites always have the \"Suppressor\" affix.",
    "Type": "Major"
  },
  {
    "IdSno": 1314335,
    "IdName": "DungeonAffix_Major_Empowered Elites (Teleporter)",
    "Name": "Empowered Elites (Teleporter)",
    "Description": "Elites always have the \"Teleporter\" affix.",
    "Type": "Major"
  },
  {
    "IdSno": 1114071,
    "IdName": "World_DGN_Hawe_FacelessShrine",
    "Name": "Faceless Shrine",
    "Description": "One of Hawezar’s less secretive cults. Sinners welcome.",
    "Type": "Dungeon"
  },
  {
    "IdSno": 1314313,
    "IdName": "DungeonAffix_Positive_FireDamage",
    "Name": "Fire Damage",
    "Description": "You deal 15% more Fire damage.",
    "Type": "Positive"
  },
  {
    "IdSno": 1113710,
    "IdName": "World_DGN_Kehj_ForgottenRuins",
    "Name": "Forgotten Ruins",
    "Description": "Serpents infest the bones of these forbidden mage halls.",
    "Type": "Dungeon"
  },
  {
    "IdSno": 1314248,
    "IdName": "DungeonAffix_Positive_FrostDamage",
    "Name": "Frost Damage",
    "Description": "You deal 15% more Frost damage.",
    "Type": "Positive"
  },
  {
    "IdSno": 1113366,
    "IdName": "World_DGN_Scos_GaranHold",
    "Name": "Garan Hold",
    "Description": "A once mighty stronghold, doomed to burn.",
    "Type": "Dungeon"
  },
  {
    "IdSno": 1314215,
    "IdName": "DungeonAffix_Positive_GoldFind",
    "Name": "Gold Find",
    "Description": "You find 30% more gold.",
    "Type": "Positive"
  },
  {
    "IdSno": 1113361,
    "IdName": "World_DGN_Kehj_HallsoftheDamned",
    "Name": "Halls of the Damned",
    "Description": "Triune mages once pioneered strange magics here...",
    "Type": "Dungeon"
  },
  {
    "IdSno": 1113270,
    "IdName": "World_DGN_Kehj_HereticsAsylum",
    "Name": "Heretics Asylum",
    "Description": "A jail home to the corrupt and cruel.",
    "Type": "Dungeon"
  },
  {
    "IdSno": 1113997,
    "IdName": "World_DGN_Frac_HoarfrostDemise",
    "Name": "Hoarfrost Demise",
    "Description": "An icy Goatman cave, littered with corpses and bones.",
    "Type": "Dungeon"
  },
  {
    "IdSno": 1113291,
    "IdName": "World_DGN_Frac_ImmortalEmanation",
    "Name": "Immortal Emanation",
    "Description": "A hunting ground, when prey is foolish enough to enter. ",
    "Type": "Dungeon"
  },
  {
    "IdSno": 1314244,
    "IdName": "DungeonAffix_Positive_IncreasedCritChance",
    "Name": "Increased Critical Strike",
    "Description": "Your Critical Strike chance is increased by 9%.",
    "Type": "Positive"
  },
  {
    "IdSno": 1314246,
    "IdName": "DungeonAffix_Positive_IncreasedHealing",
    "Name": "Increased Healing",
    "Description": "Your Healing Received is increased by 15%.",
    "Type": "Positive"
  },
  {
    "IdSno": 1113530,
    "IdName": "World_DGN_Hawe_IronHold",
    "Name": "Iron Hold",
    "Description": "A scourge stirs within the bowels of a decaying prison.",
    "Type": "Dungeon"
  },
  {
    "IdSno": 1113877,
    "IdName": "World_DGN_Step_KomdorTemple",
    "Name": "Komdor Temple",
    "Description": "A Triune sect cursed to forever walk Sanctuary as goatmen. ",
    "Type": "Dungeon"
  },
  {
    "IdSno": 1113098,
    "IdName": "World_DGN_Frac_KorValarRamparts",
    "Name": "Kor Valar Ramparts",
    "Description": "A corrupted fortress concealing the sins of the Penitents.",
    "Type": "Dungeon"
  },
  {
    "IdSno": 1314217,
    "IdName": "DungeonAffix_Positive_PeriodicLightning",
    "Name": "Lightning Caller",
    "Description": "You occasionally call down lightning strikes that damage nearby enemies.",
    "Type": "Positive"
  },
  {
    "IdSno": 1314238,
    "IdName": "DungeonAffix_Positive_LightningDamage",
    "Name": "Lightning Damage",
    "Description": "You deal 15% more Lightning damage.",
    "Type": "Positive"
  },
  {
    "IdSno": 1314209,
    "IdName": "DungeonAffix_Major_Lightning Storm",
    "Name": "Lightning Storm",
    "Description": "Lightning gathers above the player. Get into the protection dome to avoid severe outcomes.",
    "Type": "Major"
  },
  {
    "IdSno": 1113337,
    "IdName": "World_DGN_Hawe_LostKeep",
    "Name": "Lost Keep",
    "Description": "Yet another rotting keep abandoned by the Cathedral.",
    "Type": "Dungeon"
  },
  {
    "IdSno": 1314240,
    "IdName": "DungeonAffix_Positive_MagicFind",
    "Name": "Magic Find",
    "Description": "You find more items from enemies. ",
    "Type": "Positive"
  },
  {
    "IdSno": 1113188,
    "IdName": "World_DGN_Scos_MarinersRefuge",
    "Name": "Mariner's Refuge",
    "Description": "The Drowned lure shipwrecked sailors to the depths.",
    "Type": "Dungeon"
  },
  {
    "IdSno": 1314384,
    "IdName": "DungeonAffix_Minor_Monster_LessMelee",
    "Name": "Melee Defenders",
    "Description": "Monsters take 40% less damage from close targets.",
    "Type": "Minor"
  },
  {
    "IdSno": 1114168,
    "IdName": "World_DGN_Frac_MercysReach",
    "Name": "Mercy's Reach",
    "Description": "This crumbling keep was once a way through the mountains. ",
    "Type": "Dungeon"
  },
  {
    "IdSno": 1314354,
    "IdName": "DungeonAffix_Minor_Monster_AttackFaster",
    "Name": "Monster Attack Speed",
    "Description": "Monsters attack 25% faster.",
    "Type": "Minor"
  },
  {
    "IdSno": 1314452,
    "IdName": "DungeonAffix_Minor_Monster_Barrier",
    "Name": "Monster Barrier",
    "Description": "Monsters gain 30% of their Maximum Life as a Barrier.",
    "Type": "Minor"
  },
  {
    "IdSno": 1314380,
    "IdName": "DungeonAffix_Minor_Monster_LessBleeding",
    "Name": "Monster Bleed Resist",
    "Description": "Monsters take 60% less Bleeding damage.",
    "Type": "Minor"
  },
  {
    "IdSno": 1314407,
    "IdName": "DungeonAffix_Minor_Monster_ExtraBleeding",
    "Name": "Monster Bleeding Damage",
    "Description": "Monsters deal an additional 30% of their Physical damage dealt as Bleeding over 5 seconds.",
    "Type": "Minor"
  },
  {
    "IdSno": 1314409,
    "IdName": "DungeonAffix_Minor_Monster_ExtraBurning",
    "Name": "Monster Burning Damage",
    "Description": "Monsters deal an additional 30% of their Physical damage dealt as Burning over 5 seconds.",
    "Type": "Minor"
  },
  {
    "IdSno": 1314382,
    "IdName": "DungeonAffix_Minor_Monster_LessBurning",
    "Name": "Monster Burning Resist",
    "Description": "Monsters take 60% less Burning damage.",
    "Type": "Minor"
  },
  {
    "IdSno": 1314415,
    "IdName": "DungeonAffix_Minor_Monster_ExtraCold",
    "Name": "Monster Cold Damage",
    "Description": "Monsters deal an additional 20% of their Physical damage dealt as Cold.",
    "Type": "Minor"
  },
  {
    "IdSno": 1314397,
    "IdName": "DungeonAffix_Minor_Monster_LessCold",
    "Name": "Monster Cold Resist",
    "Description": "Monsters take 40% less Cold damage.",
    "Type": "Minor"
  },
  {
    "IdSno": 1314448,
    "IdName": "DungeonAffix_Minor_Monster_AntiCrit",
    "Name": "Monster Critical Resist",
    "Description": "Monsters take 60% less damage from Critical Strike.",
    "Type": "Minor"
  },
  {
    "IdSno": 1314446,
    "IdName": "DungeonAffix_Minor_Monster_AntiCC",
    "Name": "Monster Crowd Control Resist",
    "Description": "Crowd Control duration vs monsters is reduced by 40%.",
    "Type": "Minor"
  },
  {
    "IdSno": 1314424,
    "IdName": "DungeonAffix_Minor_Monster_ExtraFire",
    "Name": "Monster Fire Damage",
    "Description": "Monsters deal an additional 20% of their Physical damage dealt as Fire.",
    "Type": "Minor"
  },
  {
    "IdSno": 1314437,
    "IdName": "DungeonAffix_Minor_Monster_LessFire",
    "Name": "Monster Fire Resist",
    "Description": "Monsters take 40% less Fire damage.",
    "Type": "Minor"
  },
  {
    "IdSno": 1314356,
    "IdName": "DungeonAffix_Minor_Monster_HPBonus",
    "Name": "Monster Life",
    "Description": "Monsters gain 30% extra life.",
    "Type": "Minor"
  },
  {
    "IdSno": 1314372,
    "IdName": "DungeonAffix_Minor_Monster_LifeSteal",
    "Name": "Monster Life Steal",
    "Description": "Non-boss monsters gain 15% Life Steal.",
    "Type": "Minor"
  },
  {
    "IdSno": 1314413,
    "IdName": "DungeonAffix_Minor_Monster_ExtraLightning",
    "Name": "Monster Lightning Damage",
    "Description": "Monsters deal an additional 20% of their Physical damage dealt as Lightning.",
    "Type": "Minor"
  },
  {
    "IdSno": 1314444,
    "IdName": "DungeonAffix_Minor_Monster_AntiOverpower",
    "Name": "Monster Overpower Resist",
    "Description": "Monsters take 60% less damage from Overpower attacks.",
    "Type": "Minor"
  },
  {
    "IdSno": 1314388,
    "IdName": "DungeonAffix_Minor_Monster_LessPhysical",
    "Name": "Monster Physical Resist",
    "Description": "Monsters take 30% less Physical damage.",
    "Type": "Minor"
  },
  {
    "IdSno": 1314405,
    "IdName": "DungeonAffix_Minor_Monster_ExtraPoison",
    "Name": "Monster Poison Damage",
    "Description": "Monsters deal an additional 30% of their Physical damage dealt as Poison over 5 seconds.",
    "Type": "Minor"
  },
  {
    "IdSno": 1314393,
    "IdName": "DungeonAffix_Minor_Monster_LessPoison",
    "Name": "Monster Poison Resist",
    "Description": "Monsters take 60% less Poison damage.",
    "Type": "Minor"
  },
  {
    "IdSno": 1314454,
    "IdName": "DungeonAffix_Minor_Monster_HPRegen",
    "Name": "Monster Regen",
    "Description": "Non-boss monsters regen 1.5% Maximum Life per second.",
    "Type": "Minor"
  },
  {
    "IdSno": 1314411,
    "IdName": "DungeonAffix_Minor_Monster_ExtraShadow",
    "Name": "Monster Shadow Damage",
    "Description": "Monsters deal an additional 20% of their Physical damage dealt as Shadow.",
    "Type": "Minor"
  },
  {
    "IdSno": 1314399,
    "IdName": "DungeonAffix_Minor_Monster_ExtraCorruption",
    "Name": "Monster Shadow Damage Over Time",
    "Description": "Monsters deal an additional 30% of their Physical damage dealt as Shadow over 5 seconds.",
    "Type": "Minor"
  },
  {
    "IdSno": 1314378,
    "IdName": "DungeonAffix_Minor_Monster_LessCorruption",
    "Name": "Monster Shadow Damage Over Time Resist",
    "Description": "Monsters take 60% reduced damage from your Shadow damage over time effects.",
    "Type": "Minor"
  },
  {
    "IdSno": 1314376,
    "IdName": "DungeonAffix_Minor_Monster_LessShadow",
    "Name": "Monster Shadow Resist",
    "Description": "Monsters take 40% less Shadow damage.",
    "Type": "Minor"
  },
  {
    "IdSno": 1314360,
    "IdName": "DungeonAffix_Minor_Monster_ReflectNonPhysical",
    "Name": "Monster Thorns",
    "Description": "Monsters reflect 8% of damage.",
    "Type": "Minor"
  },
  {
    "IdSno": 1314442,
    "IdName": "DungeonAffix_Minor_Monster_AntiVulnerable",
    "Name": "Monster Vulnerable Resist",
    "Description": "Duration of Vulnerable Effects vs monsters is reduced by 60%.",
    "Type": "Minor"
  },
  {
    "IdSno": 1314395,
    "IdName": "DungeonAffix_Minor_Monster_LessLightning",
    "Name": "Monsters Lightning Resist",
    "Description": "Monsters take 40% less Lightning damage.",
    "Type": "Minor"
  },
  {
    "IdSno": 1314252,
    "IdName": "DungeonAffix_Major_Nightmare Portal",
    "Name": "Nightmare Portal",
    "Description": "While in combat, Nightmare Portals open randomly near players, pouring out dangerous monsters.",
    "Type": "Major"
  },
  {
    "IdSno": 1113695,
    "IdName": "World_DGN_Frac_NostravaDeepwood",
    "Name": "Nostrava Deepwood",
    "Description": "The undead roam among the trees.",
    "Type": "Dungeon"
  },
  {
    "IdSno": 1314391,
    "IdName": "DungeonAffix_Positive_EvadePushesEnemies",
    "Name": "Nudging Evade",
    "Description": "Using Evade pushes enemies back. ",
    "Type": "Positive"
  },
  {
    "IdSno": 1113728,
    "IdName": "World_DGN_Step_PallidDelve",
    "Name": "Pallid Delve",
    "Description": "Cannibals guard a dark power in the crumbling mines.",
    "Type": "Dungeon"
  },
  {
    "IdSno": 1113431,
    "IdName": "World_DGN_Step_PathoftheBlind",
    "Name": "Path of the Blind",
    "Description": "The bloodstained initiation grounds for Triune aspirants.",
    "Type": "Dungeon"
  },
  {
    "IdSno": 1314293,
    "IdName": "DungeonAffix_Positive_PhysicalDamage",
    "Name": "Physical Damage",
    "Description": "You deal 15% more Physical damage.",
    "Type": "Positive"
  },
  {
    "IdSno": 1314227,
    "IdName": "DungeonAffix_Positive_PoisonDamage",
    "Name": "Poison Damage",
    "Description": "You deal 15% more Poison damage.",
    "Type": "Positive"
  },
  {
    "IdSno": 1314358,
    "IdName": "DungeonAffix_Positive_EvadeLeavesPoison",
    "Name": "Poisonous Evade",
    "Description": "Using Evade leaves a pool of Poison behind that damages enemies. ",
    "Type": "Positive"
  },
  {
    "IdSno": 1314370,
    "IdName": "DungeonAffix_Minor_Monster_ReduceHealing",
    "Name": "Potion Breakers",
    "Description": "Monster attacks from a distance have 30% chance to disable healing potion for 2 seconds.",
    "Type": "Minor"
  },
  {
    "IdSno": 1314297,
    "IdName": "DungeonAffix_Positive_AttackMoveSpeedOnKill",
    "Name": "Quick Killer",
    "Description": "Killing a monster grants 2.0% Attack and Move Speed. Stacking up to 20%.",
    "Type": "Positive"
  },
  {
    "IdSno": 1314386,
    "IdName": "DungeonAffix_Minor_Monster_LessRanged",
    "Name": "Ranged Defenders",
    "Description": "Monsters take 60% less damage from distant targets.",
    "Type": "Minor"
  },
  {
    "IdSno": 1314233,
    "IdName": "DungeonAffix_Positive_CooldownReductionOnKill",
    "Name": "Reduce Cooldowns on Kill",
    "Description": "Killing a monster reduces your cooldowns by .25 seconds.",
    "Type": "Positive"
  },
  {
    "IdSno": 1314417,
    "IdName": "DungeonAffix_Minor_Monster_ReduceResistance",
    "Name": "Resistance Breakers",
    "Description": "Monster attacks from a distance reduce resistance by 10% for 6 seconds, stacking up to 50%.",
    "Type": "Minor"
  },
  {
    "IdSno": 1314364,
    "IdName": "DungeonAffix_Minor_Monster_DrainResource",
    "Name": "Resource Burn",
    "Description": "Monster attacks from a distance burn 16% of your Primary Resource.",
    "Type": "Minor"
  },
  {
    "IdSno": 1113484,
    "IdName": "World_DGN_Scos_SaratsLair",
    "Name": "Sarat's Lair",
    "Description": "What once was a wildlife den has become a nest.",
    "Type": "Dungeon"
  },
  {
    "IdSno": 1314231,
    "IdName": "DungeonAffix_Positive_ShadowDamage",
    "Name": "Shadow Damage",
    "Description": "You deal 15% more Shadow damage.",
    "Type": "Positive"
  },
  {
    "IdSno": 1113768,
    "IdName": "World_DGN_Step_ShiftingCity",
    "Name": "Shifting City",
    "Description": "These ruins were once a refuge for the people of Qara-Yisu.",
    "Type": "Dungeon"
  },
  {
    "IdSno": 1314374,
    "IdName": "DungeonAffix_Minor_Monster_ChanceSlow",
    "Name": "Slowing Projectiles",
    "Description": "Monster attacks from a distance have a 50% chance to slow targets.",
    "Type": "Minor"
  },
  {
    "IdSno": 1114089,
    "IdName": "World_DGN_Scos_Stockades",
    "Name": "Stockades",
    "Description": "After a riot, this prison was walled off and made a tomb.",
    "Type": "Dungeon"
  },
  {
    "IdSno": 1314213,
    "IdName": "DungeonAffix_Major_StormbanesWrath",
    "Name": "Stormbane's Wrath",
    "Description": "Stormbane's Wrath chases players around, releasing deadly pulses when reaching a player.",
    "Type": "Major"
  },
  {
    "IdSno": 1314236,
    "IdName": "DungeonAffix_Positive_Thorns",
    "Name": "Thorns",
    "Description": "Your Thorns are increased by 491.",
    "Type": "Positive"
  },
  {
    "IdSno": 1113343,
    "IdName": "World_DGN_Kehj_TomboftheSaints",
    "Name": "Tomb of the Saints",
    "Description": "This barren tomb was once fat with gold. ",
    "Type": "Dungeon"
  },
  {
    "IdSno": 1113763,
    "IdName": "World_DGN_Scos_TwistedHollow",
    "Name": "Twisted Hollow",
    "Description": "A veritable reservoir of wildlife where answers may lurk.",
    "Type": "Dungeon"
  },
  {
    "IdSno": 1114151,
    "IdName": "World_DGN_Kehj_UldursCave",
    "Name": "Uldur's Cave",
    "Description": "A den of murderers and carrion feeders.",
    "Type": "Dungeon"
  },
  {
    "IdSno": 1314366,
    "IdName": "DungeonAffix_Minor_Monster_Unstoppable",
    "Name": "Unstoppable Monsters",
    "Description": "Monsters become Unstoppable when life drops below 30%.",
    "Type": "Minor"
  },
  {
    "IdSno": 1314256,
    "IdName": "DungeonAffix_Major_Volcanic",
    "Name": "Volcanic",
    "Description": "While in combat, gouts of flame periodically erupt near players.",
    "Type": "Major"
  }
]